mlog_arithmetic_runner/__init__.py
mlog_arithmetic_runner/__main__.py
mlog_arithmetic_runner/arithmetic_operators.py
mlog_arithmetic_runner/memory.py
mlog_arithmetic_runner/mlog_processor.py
mlog_arithmetic_runner-0.0.5.dist-info/LICENSE
mlog_arithmetic_runner-0.0.5.dist-info/METADATA
mlog_arithmetic_runner-0.0.5.dist-info/WHEEL
mlog_arithmetic_runner-0.0.5.dist-info/top_level.txt
mlog_arithmetic_runner-0.0.5.dist-info/RECORD
