Metadata-Version: 2.1
Name: mlog-arithmetic-runner
Version: 0.0.5
Summary: An Mindustry Logic emulator built for automated testing of compilers.
Home-page: https://github.com/UMRnInside/MlogArithmeticRunner
Author: UMRnInside
Author-email: 30196401+UMRnInside@users.noreply.github.com
License: UNKNOWN
Project-URL: Bug Tracker, https://github.com/UMRnInside/MlogArithmeticRunner/issues
Platform: UNKNOWN
Classifier: Programming Language :: Python :: 3
Classifier: License :: OSI Approved :: MIT License
Classifier: Operating System :: OS Independent
Requires-Python: >=3.6
